testrail_data/__init__.py
testrail_data/_category.py
testrail_data/_testrail_api.py
testrail_data-0.0.10.dist-info/LICENSE
testrail_data-0.0.10.dist-info/METADATA
testrail_data-0.0.10.dist-info/WHEEL
testrail_data-0.0.10.dist-info/top_level.txt
testrail_data-0.0.10.dist-info/RECORD
