Metadata-Version: 2.1
Name: testrail-data
Version: 0.0.10
Summary: Pandas DataFrame integrated API wrapper for Testrail
Home-page: https://github.com/maxleow/testrail_data
Author: Max Leow
Author-email: maxengiu@outlook.com
Project-URL: Bug Tracker, https://github.com/maxleow/testrail_data/issues
Classifier: Programming Language :: Python :: 3.7
Classifier: Programming Language :: Python :: 3.8
Classifier: Programming Language :: Python :: 3.9
Classifier: Programming Language :: Python :: 3.10
Classifier: License :: OSI Approved :: MIT License
Classifier: Operating System :: OS Independent
Requires-Python: >=3.7
License-File: LICENSE
Requires-Dist: pandas
Requires-Dist: testrail-api (>=1.10)
